[{
  "_id": {
    "$oid": "664616ef4bd169d3b1f9e8b8"
  },
  "schoolYearID": "2324",
  "semesters": [
    {
      "semesterID": "232",
      "semesterName": "1"
    },
    {
      "semesterID": "241",
      "semesterName": "2"
    }
  ],
  "schoolYearName": "2023-2024"
},
{
  "_id": {
    "$oid": "664616ef4bd169d3b1f9e8b9"
  },
  "schoolYearID": "2223",
  "semesters": [
    {
      "semesterID": "222",
      "semesterName": "1"
    },
    {
      "semesterID": "231",
      "semesterName": "2"
    }
  ],
  "schoolYearName": "2022-2023"
}]